tests/__init__.py
tests/local_api_test.py
tests/models_test.py
watergate_local_api/__init__.py
watergate_local_api/watergate_api.py
watergate_local_api/models/__init__.py
watergate_local_api/models/auto_shut_off_report.py
watergate_local_api/models/auto_shut_off_state.py
watergate_local_api/models/device_state.py
watergate_local_api/models/networking.py
watergate_local_api/models/telemetry_data.py
watergate_local_api/models/water_event.py
watergate_local_api/models/water_meter.py
watergate_local_api/models/webhook_model.py
watergate_local_api-2024.4.1.dist-info/LICENSE.md
watergate_local_api-2024.4.1.dist-info/METADATA
watergate_local_api-2024.4.1.dist-info/WHEEL
watergate_local_api-2024.4.1.dist-info/top_level.txt
watergate_local_api-2024.4.1.dist-info/RECORD
