Metadata-Version: 2.1
Name: watergate-local-api
Version: 2024.4.1
Summary: Python package to interact with the Watergate Local API.
Home-page: https://github.com/hero-laboratories/watergate-local-api-python
Author: Watergate
Author-email: hi@watergate.ai
Classifier: Programming Language :: Python :: 3
Classifier: License :: OSI Approved :: GNU General Public License v3 (GPLv3)
Classifier: Operating System :: OS Independent
License-File: LICENSE.md
